{"status":"nochanged","gxr":"XJFH_P","gxsj":"20231022 14:58:04","ygxsj":"20231022 14:58:04","lrr":"SYSTEM","lrsj":"20161207 12:40:56","xsJbxxId":"2014371323010210099","grbsm":"G371323200808270022","xxJbxxId":"3713230001","xxNjxxId":"02A125C36833D2F5E063CA021CAC020E","xxBjxxId":"20233713230001308","xjfh":"2023371323000130391","bnxh":null,"xm":"李奕宁","ywxm":null,"xmpy":null,"cym":null,"xbm":"女","csrq":"2008-08-27","csdm":"371323000000","jg":"山东省临沂市沂水县","mzm":"汉族","gjdqm":"156","sfzjlxm":"1","sfzjh":"371323200808270022","gatqwm":"00","hkxzm":"2","hkszdm":"371323000000","jtzz":"沂水县山水文园小区2号楼1单元102","xzz":"沂水县山水文园小区2号楼1单元102","lxdh":"13969908335","dzxx":null,"yzbm":"276400","zzmmm":"群众","jkzkm":"健康或良好","xxm":"0","rxfsm":"11","xslbm":"32100","rxny":"202309","jdfsm":"1","xslym":"1","xsdqztm":"01","bz":null,"xxsszgjyxzdm":"3713230000","sfsc":"0","familyMemsList":[{"mzm":"01","lxdh":"13615497122","cyxm":"李生","gxm":"父亲","gzdw":"中国车安保险公司","xs_jtcy_id":"201437132301021009901"},{"mzm":"01","lxdh":"13969908335","cyxm":"董世芬","gxm":"母亲","gzdw":"兴荣制衣厂","xs_jtcy_id":"201437132301021009902"}],"xxmc":"沂水县第一中学","njmc":"高中一年级","bjmc":"2023级08班","sszgjyxzdm":null,"jxbId":null,"jxbMc":null}