{"status":"nochanged","gxr":"XJFH_P","gxsj":"20231022 14:58:02","ygxsj":"20231022 14:58:02","lrr":"SYSTEM","lrsj":"20161207 11:23:35","xsJbxxId":"2014371323050910036","grbsm":"G371323200807091727","xxJbxxId":"3713230001","xxNjxxId":"02A125C36833D2F5E063CA021CAC020E","xxBjxxId":"20233713230001302","xjfh":"2023371323000130058","bnxh":null,"xm":"刘杉","ywxm":null,"xmpy":"Liusha","cym":null,"xbm":"女","csrq":"2008-07-09","csdm":"371323000000","jg":"山东省临沂市沂水县","mzm":"汉族","gjdqm":"156","sfzjlxm":"1","sfzjh":"371323200807091727","gatqwm":"00","hkxzm":"1","hkszdm":"371323000000","jtzz":"山东省临沂市沂水县高桥镇朱家沟村","xzz":"高桥镇朱家沟村","lxdh":"15588119211","dzxx":null,"yzbm":"276411","zzmmm":"群众","jkzkm":"健康或良好","xxm":"0","rxfsm":"11","xslbm":"32100","rxny":"202309","jdfsm":"2","xslym":"1","xsdqztm":"01","bz":null,"xxsszgjyxzdm":"3713230000","sfsc":"0","familyMemsList":[{"mzm":"01","lxdh":"15588119211","cyxm":"刘洪明","gxm":"父亲","gzdw":"山东省临沂市沂水县高桥镇朱家沟宋村委会","xs_jtcy_id":"201437132305091003601"},{"mzm":"01","lxdh":"15588119211","cyxm":"李桂连","gxm":"母亲","gzdw":"山东省沂水县高桥镇朱家沟村","xs_jtcy_id":"201437132305091003602"}],"xxmc":"沂水县第一中学","njmc":"高中一年级","bjmc":"2023级02班","sszgjyxzdm":null,"jxbId":null,"jxbMc":null}