{"status":"nochanged","gxr":"XJFH_P","gxsj":"20231022 14:58:06","ygxsj":"20231022 14:58:06","lrr":"SYSTEM","lrsj":"20180110 06:59:24","xsJbxxId":"2013371323010410081","grbsm":"G411525200706173930","xxJbxxId":"3713230001","xxNjxxId":"02A125C36833D2F5E063CA021CAC020E","xxBjxxId":"20233713230001319","xjfh":"2023371323000130972","bnxh":null,"xm":"曹云畅","ywxm":null,"xmpy":"Caoyunchang","cym":null,"xbm":"男","csrq":"2007-06-17","csdm":"411525000000","jg":"河南省","mzm":"汉族","gjdqm":"156","sfzjlxm":"1","sfzjh":"411525200706173930","gatqwm":"00","hkxzm":"1","hkszdm":"411525000000","jtzz":"沂水东方巴黎城","xzz":"沂水县东方巴黎城小区6号楼3单元802室","lxdh":"15153949703","dzxx":null,"yzbm":"276400","zzmmm":"群众","jkzkm":"健康或良好","xxm":"0","rxfsm":"11","xslbm":"32100","rxny":"202309","jdfsm":"1","xslym":"1","xsdqztm":"01","bz":null,"xxsszgjyxzdm":"3713230000","sfsc":"0","familyMemsList":[{"mzm":"01","lxdh":"15153949703","cyxm":"曹俊","gxm":"父亲","gzdw":"个体","xs_jtcy_id":"65a958b648c94fc7a4e742c32d7bc8ae"},{"mzm":"01","lxdh":"15854988565","cyxm":"姜士莉","gxm":"母亲","gzdw":"个体","xs_jtcy_id":"a3bc080c6a2b43bc894b0340246bc0fe"}],"xxmc":"沂水县第一中学","njmc":"高中一年级","bjmc":"2023级19班","sszgjyxzdm":null,"jxbId":null,"jxbMc":null}